filterutil/__init__.py
filterutil/applying.py
filterutil/compound_filter.py
filterutil/filters.py
filterutil/logic_gate.py
filterutil/nand_filters.py
filterutil/nor_filters.py
filterutil/or_filters.py
filterutil/simple_filter.py
filterutil/xnor_filters.py
filterutil/xor_filters.py
filterutil-2.0.2.dist-info/METADATA
filterutil-2.0.2.dist-info/WHEEL
filterutil-2.0.2.dist-info/licenses/LICENSE
filterutil-2.0.2.dist-info/RECORD
