Metadata-Version: 2.4
Name: filterutil
Version: 2.0.2
Summary: Let you register and use filters in right way
Project-URL: Github repo, https://github.com/akvilary/filterutil
Project-URL: Bug tracker, https://github.com/akvilary/filterutil/issues
Project-URL: Release notes in Telegram, https://t.me/filterutil
Author-email: Andrey Smirnov <smirnovcode@mail.ru>
License-File: LICENSE
Classifier: License :: CC0 1.0 Universal (CC0 1.0) Public Domain Dedication
Classifier: Operating System :: OS Independent
Classifier: Programming Language :: Python :: 3
Requires-Python: >=3.11
